iran_kish_payment/__init__.py
iran_kish_payment/aes_encryptor.py
iran_kish_payment/b_str_generator.py
iran_kish_payment/payment_requester.py
iran_kish_payment/payment_verifier.py
iran_kish_payment/rsa_encryptor.py
iran_kish_payment/server_requester.py
iran_kish_payment/sha256_hasher.py
iran_kish_payment/verify.py
iran_kish_payment-1.0.0.dist-info/LICENSE
iran_kish_payment-1.0.0.dist-info/METADATA
iran_kish_payment-1.0.0.dist-info/WHEEL
iran_kish_payment-1.0.0.dist-info/top_level.txt
iran_kish_payment-1.0.0.dist-info/RECORD
